{
  "платье женское": [
    {
      "2023 Январь": 2134335
    },
    {
      "2023 Февраль": 4823476
    },
    {
      "2023 Март": 5685264
    },
    {
      "2023 Апрель": 4339284
    },
    {
      "2023 Май": 4563556
    },
    {
      "2023 Июнь": 3321474
    },
    {
      "2023 Июль": 2100989
    },
    {
      "2023 Август": 2267632
    },
    {
      "2023 Сентябрь": 1971237
    },
    {
      "2023 Октябрь": 2494522
    },
    {
      "2023 Ноябрь": 3870076
    },
    {
      "2023 Декабрь": 4162401
    },
    {
      "2024 Январь": 2582551
    },
    {
      "2024 Февраль": 3037964
    },
    {
      "2024 Март": 3307406
    },
    {
      "2024 Апрель": 2926477
    },
    {
      "2024 Май": 2498794
    },
    {
      "2024 Июнь": 1471783
    },
    {
      "2024 Июль": 1345912
    },
    {
      "2024 Август": 1602679
    },
    {
      "2024 Сентябрь": 1750964
    },
    {
      "2024 Октябрь": 2074906
    },
    {
      "2024 Ноябрь": 2616781
    },
    {
      "2024 Декабрь": 3386235
    },
    {
      "2025 Январь": 2250066
    },
    {
      "2025 Февраль": 1804463
    },
    {
      "2025 Март": 1515631
    },
    {
      "2025 Апрель": 2131740
    },
    {
      "2025 Май": 1781732
    },
    {
      "2025 Июнь": 1112753
    },
    {
      "2025 Июль": 1036283
    },
    {
      "2025 Август": 1176102
    },
    {
      "2025 Сентябрь": 1256233
    }
  ]
}